[{"inputs":[],"stateMutability":"nonpayable","type":"constructor"},{"anonymous":false,"inputs":[{"indexed":false,"internalType":"address","name":"previousAdmin","type":"address"},{"indexed":false,"internalType":"address","name":"newAdmin","type":"address"}],"name":"AdminChanged","type":"event"},{"anonymous":false,"inputs":[{"indexed":true,"internalType":"address","name":"mw","type":"address"},{"indexed":true,"internalType":"bool","name":"preAllowed","type":"bool"},{"indexed":true,"internalType":"bool","name":"newAllowed","type":"bool"}],"name":"AllowEssenceMw","type":"event"},{"anonymous":false,"inputs":[{"indexed":true,"internalType":"address","name":"mw","type":"address"},{"indexed":true,"internalType":"bool","name":"preAllowed","type":"bool"},{"indexed":true,"internalType":"bool","name":"newAllowed","type":"bool"}],"name":"AllowSubscribeMw","type":"event"},{"anonymous":false,"inputs":[{"indexed":true,"internalType":"address","name":"owner","type":"address"},{"indexed":true,"internalType":"address","name":"spender","type":"address"},{"indexed":true,"internalType":"uint256","name":"id","type":"uint256"}],"name":"Approval","type":"event"},{"anonymous":false,"inputs":[{"indexed":true,"internalType":"address","name":"owner","type":"address"},{"indexed":true,"internalType":"address","name":"operator","type":"address"},{"indexed":false,"internalType":"bool","name":"approved","type":"bool"}],"name":"ApprovalForAll","type":"event"},{"anonymous":false,"inputs":[{"indexed":true,"internalType":"address","name":"user","type":"address"},{"indexed":true,"internalType":"contract Authority","name":"newAuthority","type":"address"}],"name":"AuthorityUpdated","type":"event"},{"anonymous":false,"inputs":[{"indexed":true,"internalType":"address","name":"beacon","type":"address"}],"name":"BeaconUpgraded","type":"event"},{"anonymous":false,"inputs":[{"indexed":true,"internalType":"address","name":"owner","type":"address"}],"name":"Initialize","type":"event"},{"anonymous":false,"inputs":[{"indexed":true,"internalType":"address","name":"user","type":"address"},{"indexed":true,"internalType":"address","name":"newOwner","type":"address"}],"name":"OwnerUpdated","type":"event"},{"anonymous":false,"inputs":[{"indexed":false,"internalType":"address","name":"account","type":"address"}],"name":"Paused","type":"event"},{"anonymous":false,"inputs":[{"indexed":true,"internalType":"string","name":"newTemplate","type":"string"}],"name":"SetAnimationTemplate","type":"event"},{"anonymous":false,"inputs":[{"indexed":true,"internalType":"uint256","name":"profileId","type":"uint256"},{"indexed":true,"internalType":"string","name":"newAvatar","type":"string"}],"name":"SetAvatar","type":"event"},{"anonymous":false,"inputs":[{"indexed":true,"internalType":"address","name":"preBoxAddr","type":"address"},{"indexed":true,"internalType":"address","name":"newBoxAddress","type":"address"}],"name":"SetBoxAddress","type":"event"},{"anonymous":false,"inputs":[{"indexed":true,"internalType":"uint256","name":"profileId","type":"uint256"},{"indexed":false,"internalType":"string","name":"newMetadata","type":"string"}],"name":"SetMetadata","type":"event"},{"anonymous":false,"inputs":[{"indexed":true,"internalType":"address","name":"newDescriptor","type":"address"}],"name":"SetNFTDescriptor","type":"event"},{"anonymous":false,"inputs":[{"indexed":true,"internalType":"uint256","name":"profileId","type":"uint256"},{"indexed":true,"internalType":"address","name":"operator","type":"address"},{"indexed":false,"internalType":"bool","name":"prevApproved","type":"bool"},{"indexed":false,"internalType":"bool","name":"approved","type":"bool"}],"name":"SetOperatorApproval","type":"event"},{"anonymous":false,"inputs":[{"indexed":true,"internalType":"address","name":"user","type":"address"},{"indexed":true,"internalType":"uint256","name":"profileId","type":"uint256"}],"name":"SetPrimaryProfile","type":"event"},{"anonymous":false,"inputs":[{"indexed":true,"internalType":"uint256","name":"profileId","type":"uint256"},{"indexed":false,"internalType":"address","name":"mw","type":"address"},{"indexed":false,"internalType":"bytes","name":"prepareReturnData","type":"bytes"}],"name":"SetSubscribeMw","type":"event"},{"anonymous":false,"inputs":[{"indexed":true,"internalType":"uint256","name":"profileId","type":"uint256"},{"indexed":false,"internalType":"string","name":"subscribeTokenURI","type":"string"}],"name":"SetSubscribeTokenURI","type":"event"},{"anonymous":false,"inputs":[{"indexed":true,"internalType":"address","name":"from","type":"address"},{"indexed":true,"internalType":"address","name":"to","type":"address"},{"indexed":true,"internalType":"uint256","name":"id","type":"uint256"}],"name":"Transfer","type":"event"},{"anonymous":false,"inputs":[{"indexed":false,"internalType":"address","name":"account","type":"address"}],"name":"Unpaused","type":"event"},{"anonymous":false,"inputs":[{"indexed":true,"internalType":"address","name":"implementation","type":"address"}],"name":"Upgraded","type":"event"},{"inputs":[],"name":"DOMAIN_SEPARATOR","outputs":[{"internalType":"bytes32","name":"","type":"bytes32"}],"stateMutability":"view","type":"function"},{"inputs":[],"name":"ENGINE","outputs":[{"internalType":"address","name":"","type":"address"}],"stateMutability":"view","type":"function"},{"inputs":[],"name":"ESSENCE_BEACON","outputs":[{"internalType":"address","name":"","type":"address"}],"stateMutability":"view","type":"function"},{"inputs":[],"name":"SUBSCRIBE_BEACON","outputs":[{"internalType":"address","name":"","type":"address"}],"stateMutability":"view","type":"function"},{"inputs":[{"internalType":"address","name":"mw","type":"address"},{"internalType":"bool","name":"allowed","type":"bool"}],"name":"allowEssenceMw","outputs":[],"stateMutability":"nonpayable","type":"function"},{"inputs":[{"internalType":"address","name":"mw","type":"address"},{"internalType":"bool","name":"allowed","type":"bool"}],"name":"allowSubscribeMw","outputs":[],"stateMutability":"nonpayable","type":"function"},{"inputs":[{"internalType":"address","name":"spender","type":"address"},{"internalType":"uint256","name":"id","type":"uint256"}],"name":"approve","outputs":[],"stateMutability":"nonpayable","type":"function"},{"inputs":[],"name":"authority","outputs":[{"internalType":"contract Authority","name":"","type":"address"}],"stateMutability":"view","type":"function"},{"inputs":[{"internalType":"address","name":"owner","type":"address"}],"name":"balanceOf","outputs":[{"internalType":"uint256","name":"","type":"uint256"}],"stateMutability":"view","type":"function"},{"inputs":[{"internalType":"uint256","name":"profileId","type":"uint256"},{"internalType":"uint256","name":"essenceId","type":"uint256"},{"internalType":"bytes","name":"preData","type":"bytes"},{"internalType":"bytes","name":"postData","type":"bytes"}],"name":"collect","outputs":[{"internalType":"uint256","name":"tokenId","type":"uint256"}],"stateMutability":"nonpayable","type":"function"},{"inputs":[{"internalType":"uint256","name":"profileId","type":"uint256"},{"internalType":"uint256","name":"essenceId","type":"uint256"},{"internalType":"bytes","name":"preData","type":"bytes"},{"internalType":"bytes","name":"postData","type":"bytes"},{"internalType":"address","name":"sender","type":"address"},{"components":[{"internalType":"uint8","name":"v","type":"uint8"},{"internalType":"bytes32","name":"r","type":"bytes32"},{"internalType":"bytes32","name":"s","type":"bytes32"},{"internalType":"uint256","name":"deadline","type":"uint256"}],"internalType":"struct DataTypes.EIP712Signature","name":"sig","type":"tuple"}],"name":"collectWithSig","outputs":[{"internalType":"uint256","name":"tokenId","type":"uint256"}],"stateMutability":"nonpayable","type":"function"},{"inputs":[{"components":[{"internalType":"address","name":"to","type":"address"},{"internalType":"string","name":"handle","type":"string"},{"internalType":"string","name":"avatar","type":"string"},{"internalType":"string","name":"metadata","type":"string"}],"internalType":"struct DataTypes.CreateProfileParams","name":"params","type":"tuple"},{"internalType":"bytes","name":"data","type":"bytes"}],"name":"createProfile","outputs":[{"internalType":"uint256","name":"","type":"uint256"}],"stateMutability":"payable","type":"function"},{"inputs":[{"internalType":"uint256","name":"","type":"uint256"}],"name":"getApproved","outputs":[{"internalType":"address","name":"","type":"address"}],"stateMutability":"view","type":"function"},{"inputs":[{"internalType":"uint256","name":"profileId","type":"uint256"}],"name":"getAvatar","outputs":[{"internalType":"string","name":"","type":"string"}],"stateMutability":"view","type":"function"},{"inputs":[{"internalType":"uint256","name":"profileId","type":"uint256"},{"internalType":"uint256","name":"essenceId","type":"uint256"}],"name":"getEssenceNFT","outputs":[{"internalType":"address","name":"","type":"address"}],"stateMutability":"view","type":"function"},{"inputs":[{"internalType":"uint256","name":"profileId","type":"uint256"},{"internalType":"uint256","name":"essenceId","type":"uint256"}],"name":"getEssenceNFTTokenURI","outputs":[{"internalType":"string","name":"","type":"string"}],"stateMutability":"view","type":"function"},{"inputs":[{"internalType":"uint256","name":"profileId","type":"uint256"}],"name":"getHandleByProfileId","outputs":[{"internalType":"string","name":"","type":"string"}],"stateMutability":"view","type":"function"},{"inputs":[{"internalType":"uint256","name":"profileId","type":"uint256"}],"name":"getMetadata","outputs":[{"internalType":"string","name":"","type":"string"}],"stateMutability":"view","type":"function"},{"inputs":[],"name":"getNFTDescriptor","outputs":[{"internalType":"address","name":"","type":"address"}],"stateMutability":"view","type":"function"},{"inputs":[{"internalType":"uint256","name":"profileId","type":"uint256"},{"internalType":"address","name":"operator","type":"address"}],"name":"getOperatorApproval","outputs":[{"internalType":"bool","name":"","type":"bool"}],"stateMutability":"view","type":"function"},{"inputs":[{"internalType":"address","name":"user","type":"address"}],"name":"getPrimaryProfile","outputs":[{"internalType":"uint256","name":"","type":"uint256"}],"stateMutability":"view","type":"function"},{"inputs":[{"internalType":"string","name":"handle","type":"string"}],"name":"getProfileIdByHandle","outputs":[{"internalType":"uint256","name":"","type":"uint256"}],"stateMutability":"view","type":"function"},{"inputs":[{"internalType":"uint256","name":"profileId","type":"uint256"}],"name":"getSubscribeMw","outputs":[{"internalType":"address","name":"","type":"address"}],"stateMutability":"view","type":"function"},{"inputs":[{"internalType":"uint256","name":"profileId","type":"uint256"}],"name":"getSubscribeNFT","outputs":[{"internalType":"address","name":"","type":"address"}],"stateMutability":"view","type":"function"},{"inputs":[{"internalType":"uint256","name":"profileId","type":"uint256"}],"name":"getSubscribeNFTTokenURI","outputs":[{"internalType":"string","name":"","type":"string"}],"stateMutability":"view","type":"function"},{"inputs":[{"internalType":"address","name":"_owner","type":"address"},{"internalType":"string","name":"name","type":"string"},{"internalType":"string","name":"symbol","type":"string"},{"internalType":"address","name":"nftDescriptor","type":"address"},{"internalType":"contract RolesAuthority","name":"_rolesAuthority","type":"address"}],"name":"initialize","outputs":[],"stateMutability":"nonpayable","type":"function"},{"inputs":[{"internalType":"address","name":"","type":"address"},{"internalType":"address","name":"","type":"address"}],"name":"isApprovedForAll","outputs":[{"internalType":"bool","name":"","type":"bool"}],"stateMutability":"view","type":"function"},{"inputs":[{"internalType":"address","name":"mw","type":"address"}],"name":"isEssenceMwAllowed","outputs":[{"internalType":"bool","name":"","type":"bool"}],"stateMutability":"view","type":"function"},{"inputs":[{"internalType":"address","name":"mw","type":"address"}],"name":"isSubscribeMwAllowed","outputs":[{"internalType":"bool","name":"","type":"bool"}],"stateMutability":"view","type":"function"},{"inputs":[],"name":"name","outputs":[{"internalType":"string","name":"","type":"string"}],"stateMutability":"view","type":"function"},{"inputs":[{"internalType":"address","name":"","type":"address"}],"name":"nonces","outputs":[{"internalType":"uint256","name":"","type":"uint256"}],"stateMutability":"view","type":"function"},{"inputs":[],"name":"owner","outputs":[{"internalType":"address","name":"","type":"address"}],"stateMutability":"view","type":"function"},{"inputs":[{"internalType":"uint256","name":"id","type":"uint256"}],"name":"ownerOf","outputs":[{"internalType":"address","name":"owner","type":"address"}],"stateMutability":"view","type":"function"},{"inputs":[{"internalType":"bool","name":"toPause","type":"bool"}],"name":"pause","outputs":[],"stateMutability":"nonpayable","type":"function"},{"inputs":[],"name":"paused","outputs":[{"internalType":"bool","name":"","type":"bool"}],"stateMutability":"view","type":"function"},{"inputs":[{"internalType":"address","name":"spender","type":"address"},{"internalType":"uint256","name":"tokenId","type":"uint256"},{"components":[{"internalType":"uint8","name":"v","type":"uint8"},{"internalType":"bytes32","name":"r","type":"bytes32"},{"internalType":"bytes32","name":"s","type":"bytes32"},{"internalType":"uint256","name":"deadline","type":"uint256"}],"internalType":"struct DataTypes.EIP712Signature","name":"sig","type":"tuple"}],"name":"permit","outputs":[],"stateMutability":"nonpayable","type":"function"},{"inputs":[],"name":"proxiableUUID","outputs":[{"internalType":"bytes32","name":"","type":"bytes32"}],"stateMutability":"view","type":"function"},{"inputs":[{"internalType":"uint256","name":"profileId","type":"uint256"},{"internalType":"string","name":"name","type":"string"},{"internalType":"string","name":"symbol","type":"string"},{"internalType":"string","name":"essenceTokenURI","type":"string"},{"internalType":"address","name":"essenceMw","type":"address"},{"internalType":"bytes","name":"initData","type":"bytes"}],"name":"registerEssence","outputs":[{"internalType":"uint256","name":"","type":"uint256"}],"stateMutability":"nonpayable","type":"function"},{"inputs":[{"internalType":"address","name":"from","type":"address"},{"internalType":"address","name":"to","type":"address"},{"internalType":"uint256","name":"id","type":"uint256"}],"name":"safeTransferFrom","outputs":[],"stateMutability":"nonpayable","type":"function"},{"inputs":[{"internalType":"address","name":"from","type":"address"},{"internalType":"address","name":"to","type":"address"},{"internalType":"uint256","name":"id","type":"uint256"},{"internalType":"bytes","name":"data","type":"bytes"}],"name":"safeTransferFrom","outputs":[],"stateMutability":"nonpayable","type":"function"},{"inputs":[{"internalType":"string","name":"template","type":"string"}],"name":"setAnimationTemplate","outputs":[],"stateMutability":"nonpayable","type":"function"},{"inputs":[{"internalType":"address","name":"operator","type":"address"},{"internalType":"bool","name":"approved","type":"bool"}],"name":"setApprovalForAll","outputs":[],"stateMutability":"nonpayable","type":"function"},{"inputs":[{"internalType":"contract Authority","name":"newAuthority","type":"address"}],"name":"setAuthority","outputs":[],"stateMutability":"nonpayable","type":"function"},{"inputs":[{"internalType":"uint256","name":"profileId","type":"uint256"},{"internalType":"string","name":"avatar","type":"string"}],"name":"setAvatar","outputs":[],"stateMutability":"nonpayable","type":"function"},{"inputs":[{"internalType":"uint256","name":"profileId","type":"uint256"},{"internalType":"string","name":"metadata","type":"string"}],"name":"setMetadata","outputs":[],"stateMutability":"nonpayable","type":"function"},{"inputs":[{"internalType":"uint256","name":"profileId","type":"uint256"},{"internalType":"string","name":"metadata","type":"string"},{"components":[{"internalType":"uint8","name":"v","type":"uint8"},{"internalType":"bytes32","name":"r","type":"bytes32"},{"internalType":"bytes32","name":"s","type":"bytes32"},{"internalType":"uint256","name":"deadline","type":"uint256"}],"internalType":"struct DataTypes.EIP712Signature","name":"sig","type":"tuple"}],"name":"setMetadataWithSig","outputs":[],"stateMutability":"nonpayable","type":"function"},{"inputs":[{"internalType":"address","name":"descriptor","type":"address"}],"name":"setNFTDescriptor","outputs":[],"stateMutability":"nonpayable","type":"function"},{"inputs":[{"internalType":"uint256","name":"profileId","type":"uint256"},{"internalType":"address","name":"operator","type":"address"},{"internalType":"bool","name":"approved","type":"bool"}],"name":"setOperatorApproval","outputs":[],"stateMutability":"nonpayable","type":"function"},{"inputs":[{"internalType":"uint256","name":"profileId","type":"uint256"},{"internalType":"address","name":"operator","type":"address"},{"internalType":"bool","name":"approved","type":"bool"},{"components":[{"internalType":"uint8","name":"v","type":"uint8"},{"internalType":"bytes32","name":"r","type":"bytes32"},{"internalType":"bytes32","name":"s","type":"bytes32"},{"internalType":"uint256","name":"deadline","type":"uint256"}],"internalType":"struct DataTypes.EIP712Signature","name":"sig","type":"tuple"}],"name":"setOperatorApprovalWithSig","outputs":[],"stateMutability":"nonpayable","type":"function"},{"inputs":[{"internalType":"address","name":"newOwner","type":"address"}],"name":"setOwner","outputs":[],"stateMutability":"nonpayable","type":"function"},{"inputs":[{"internalType":"uint256","name":"profileId","type":"uint256"}],"name":"setPrimaryProfile","outputs":[],"stateMutability":"nonpayable","type":"function"},{"inputs":[{"internalType":"uint256","name":"profileId","type":"uint256"},{"internalType":"address","name":"mw","type":"address"},{"internalType":"bytes","name":"prepareData","type":"bytes"}],"name":"setSubscribeMw","outputs":[],"stateMutability":"nonpayable","type":"function"},{"inputs":[{"internalType":"uint256","name":"profileId","type":"uint256"},{"internalType":"string","name":"subscribeTokenURI","type":"string"}],"name":"setSubscribeTokenURI","outputs":[],"stateMutability":"nonpayable","type":"function"},{"inputs":[{"internalType":"uint256[]","name":"profileIds","type":"uint256[]"},{"internalType":"bytes[]","name":"preDatas","type":"bytes[]"},{"internalType":"bytes[]","name":"postDatas","type":"bytes[]"}],"name":"subscribe","outputs":[{"internalType":"uint256[]","name":"","type":"uint256[]"}],"stateMutability":"nonpayable","type":"function"},{"inputs":[{"internalType":"uint256[]","name":"profileIds","type":"uint256[]"},{"internalType":"bytes[]","name":"preDatas","type":"bytes[]"},{"internalType":"bytes[]","name":"postDatas","type":"bytes[]"},{"internalType":"address","name":"sender","type":"address"},{"components":[{"internalType":"uint8","name":"v","type":"uint8"},{"internalType":"bytes32","name":"r","type":"bytes32"},{"internalType":"bytes32","name":"s","type":"bytes32"},{"internalType":"uint256","name":"deadline","type":"uint256"}],"internalType":"struct DataTypes.EIP712Signature","name":"sig","type":"tuple"}],"name":"subscribeWithSig","outputs":[{"internalType":"uint256[]","name":"","type":"uint256[]"}],"stateMutability":"nonpayable","type":"function"},{"inputs":[{"internalType":"bytes4","name":"interfaceId","type":"bytes4"}],"name":"supportsInterface","outputs":[{"internalType":"bool","name":"","type":"bool"}],"stateMutability":"view","type":"function"},{"inputs":[],"name":"symbol","outputs":[{"internalType":"string","name":"","type":"string"}],"stateMutability":"view","type":"function"},{"inputs":[{"internalType":"uint256","name":"tokenId","type":"uint256"}],"name":"tokenURI","outputs":[{"internalType":"string","name":"","type":"string"}],"stateMutability":"view","type":"function"},{"inputs":[],"name":"totalSupply","outputs":[{"internalType":"uint256","name":"","type":"uint256"}],"stateMutability":"view","type":"function"},{"inputs":[{"internalType":"address","name":"from","type":"address"},{"internalType":"address","name":"to","type":"address"},{"internalType":"uint256","name":"id","type":"uint256"}],"name":"transferFrom","outputs":[],"stateMutability":"nonpayable","type":"function"},{"inputs":[{"internalType":"address","name":"newImplementation","type":"address"}],"name":"upgradeTo","outputs":[],"stateMutability":"nonpayable","type":"function"},{"inputs":[{"internalType":"address","name":"newImplementation","type":"address"},{"internalType":"bytes","name":"data","type":"bytes"}],"name":"upgradeToAndCall","outputs":[],"stateMutability":"payable","type":"function"},{"inputs":[],"name":"version","outputs":[{"internalType":"uint256","name":"","type":"uint256"}],"stateMutability":"pure","type":"function"}]